uniutils/__init__.py
uniutils/matrix.py
uniutils/tree.py
uniutils-0.1.8a0.dist-info/DESCRIPTION.rst
uniutils-0.1.8a0.dist-info/METADATA
uniutils-0.1.8a0.dist-info/RECORD
uniutils-0.1.8a0.dist-info/WHEEL
uniutils-0.1.8a0.dist-info/metadata.json
uniutils-0.1.8a0.dist-info/top_level.txt
