Metadata-Version: 2.0
Name: uniutils
Version: 0.1.8a0
Summary: Utilitys for University
Home-page: https://github.com/sciccolella/uniutils
Author: Simone Ciccolella
Author-email: ciccolella.simone@gmail.com
License: CC BY-NC 3.0
Platform: UNKNOWN
